colorwheels/__init__.py
colorwheels/color_item.py
colorwheels/colorwheels.py
colorwheels/colorwheels_config.py
colorwheels/config.py
colorwheels/singleton.py
colorwheels/wheel_item.py
colorwheels-0.7.3.dist-info/LICENSE
colorwheels-0.7.3.dist-info/METADATA
colorwheels-0.7.3.dist-info/WHEEL
colorwheels-0.7.3.dist-info/top_level.txt
colorwheels-0.7.3.dist-info/RECORD
