Metadata-Version: 2.1
Name: colorwheels
Version: 0.7.3
Summary: colorwheels - an endless color generator
Home-page: https://github.com/quantumspaces/colorwheels
Author: Quantum Spaces
Author-email: quantumspaces@outlook.com
License: UNKNOWN
Project-URL: Bug Reports, https://github.com/quantumspaces/colorwheels/issues
Project-URL: Source, https://github.com/quantumspaces/colorwheels
Keywords: development,color
Platform: UNKNOWN
Classifier: Development Status :: 4 - Beta
Classifier: Intended Audience :: Developers
Classifier: Topic :: Software Development :: Libraries :: Python Modules
Classifier: License :: OSI Approved :: MIT License
Classifier: Programming Language :: Python :: 3.7
Classifier: Programming Language :: Python :: 3.8
Classifier: Programming Language :: Python :: 3.9
Classifier: Programming Language :: Python :: 3 :: Only
Requires-Python: >=3.7, <4
License-File: LICENSE
Requires-Dist: dataclasses-json
Requires-Dist: PyYAML
Provides-Extra: dev
Requires-Dist: check-manifest ; extra == 'dev'
Provides-Extra: test
Requires-Dist: coverage ; extra == 'test'
